{
  "id": "62c208c0-4a12-4862-8a6c-601e5f303bf3",
  "prevId": "00000000-0000-0000-0000-000000000000",
  "version": "7",
  "dialect": "postgresql",
  "tables": {
    "public.transactions": {
      "name": "transactions",
      "schema": "",
      "columns": {
        "id": {
          "name": "id",
          "type": "uuid",
          "primaryKey": true,
          "notNull": true,
          "default": "gen_random_uuid()"
        },
        "user_id": {
          "name": "user_id",
          "type": "uuid",
          "primaryKey": false,
          "notNull": true
        },
        "type": {
          "name": "type",
          "type": "varchar(20)",
          "primaryKey": false,
          "notNull": true
        },
        "recipient_phone": {
          "name": "recipient_phone",
          "type": "varchar(20)",
          "primaryKey": false,
          "notNull": true
        },
        "recipient_wallet": {
          "name": "recipient_wallet",
          "type": "varchar(42)",
          "primaryKey": false,
          "notNull": false
        },
        "amount_ngn": {
          "name": "amount_ngn",
          "type": "numeric(15, 2)",
          "primaryKey": false,
          "notNull": true
        },
        "amount_cngn": {
          "name": "amount_cngn",
          "type": "bigint",
          "primaryKey": false,
          "notNull": true
        },
        "tx_hash": {
          "name": "tx_hash",
          "type": "varchar(66)",
          "primaryKey": false,
          "notNull": false
        },
        "status": {
          "name": "status",
          "type": "varchar(20)",
          "primaryKey": false,
          "notNull": true
        },
        "metadata": {
          "name": "metadata",
          "type": "jsonb",
          "primaryKey": false,
          "notNull": false
        },
        "created_at": {
          "name": "created_at",
          "type": "timestamp",
          "primaryKey": false,
          "notNull": true,
          "default": "now()"
        }
      },
      "indexes": {},
      "foreignKeys": {
        "transactions_user_id_users_id_fk": {
          "name": "transactions_user_id_users_id_fk",
          "tableFrom": "transactions",
          "tableTo": "users",
          "columnsFrom": [
            "user_id"
          ],
          "columnsTo": [
            "id"
          ],
          "onDelete": "cascade",
          "onUpdate": "no action"
        }
      },
      "compositePrimaryKeys": {},
      "uniqueConstraints": {
        "transactions_tx_hash_unique": {
          "name": "transactions_tx_hash_unique",
          "nullsNotDistinct": false,
          "columns": [
            "tx_hash"
          ]
        }
      },
      "policies": {},
      "checkConstraints": {},
      "isRLSEnabled": false
    },
    "public.users": {
      "name": "users",
      "schema": "",
      "columns": {
        "id": {
          "name": "id",
          "type": "uuid",
          "primaryKey": true,
          "notNull": true,
          "default": "gen_random_uuid()"
        },
        "phone_number": {
          "name": "phone_number",
          "type": "varchar(20)",
          "primaryKey": false,
          "notNull": true
        },
        "wallet_address": {
          "name": "wallet_address",
          "type": "varchar(42)",
          "primaryKey": false,
          "notNull": false
        },
        "created_at": {
          "name": "created_at",
          "type": "timestamp",
          "primaryKey": false,
          "notNull": true,
          "default": "now()"
        }
      },
      "indexes": {},
      "foreignKeys": {},
      "compositePrimaryKeys": {},
      "uniqueConstraints": {
        "users_phone_number_unique": {
          "name": "users_phone_number_unique",
          "nullsNotDistinct": false,
          "columns": [
            "phone_number"
          ]
        }
      },
      "policies": {},
      "checkConstraints": {},
      "isRLSEnabled": false
    }
  },
  "enums": {},
  "schemas": {},
  "sequences": {},
  "roles": {},
  "policies": {},
  "views": {},
  "_meta": {
    "columns": {},
    "schemas": {},
    "tables": {}
  }
}